Makefile
README.md
setup.py
nauty/COPYRIGHT
nauty/NRswitchg
nauty/NRswitchg.c
nauty/README
nauty/README_24
nauty/This_is_nauty26r12
nauty/addedgeg
nauty/addedgeg.c
nauty/amtog
nauty/amtog.c
nauty/biplabg
nauty/biplabg.c
nauty/bliss2dre.c
nauty/blisstog.c
nauty/callgeng.c
nauty/catg
nauty/catg.c
nauty/changes24-26.txt
nauty/checks6.c
nauty/complg
nauty/complg.c
nauty/config.guess
nauty/config.sub
nauty/config.txt
nauty/configure
nauty/configure.ac
nauty/converseg
nauty/converseg.c
nauty/copyg
nauty/copyg.c
nauty/countg
nauty/cubhamg
nauty/cubhamg.c
nauty/deledgeg
nauty/deledgeg.c
nauty/delptg
nauty/delptg.c
nauty/directg
nauty/directg.c
nauty/dreadnaut
nauty/dreadnaut.c
nauty/dretodot
nauty/dretodot.c
nauty/dretog
nauty/dretog.c
nauty/formats.txt
nauty/genbg
nauty/genbg.c
nauty/genbgL
nauty/geng
nauty/geng.c
nauty/genquarticg
nauty/genquarticg.c
nauty/genrang
nauty/genrang.c
nauty/genspecialg
nauty/genspecialg.c
nauty/gentourng
nauty/gentourng.c
nauty/gentreeg
nauty/gentreeg.c
nauty/gtnauty.c
nauty/gtools-h.in
nauty/gtools.c
nauty/gtools.h
nauty/gutil1.c
nauty/gutil2.c
nauty/gutils.h
nauty/hamheuristic
nauty/hamheuristic.c
nauty/install-sh
nauty/labelg
nauty/labelg.c
nauty/linegraphg
nauty/linegraphg.c
nauty/listg
nauty/listg.c
nauty/makefile
nauty/makefile.basic
nauty/makefile.in
nauty/multig
nauty/multig.c
nauty/naucompare.c
nauty/naugraph.c
nauty/naugroup.c
nauty/naugroup.h
nauty/naugstrings.c
nauty/naugstrings.h
nauty/naurng.c
nauty/naurng.h
nauty/nausparse.c
nauty/nausparse.h
nauty/nautaux.c
nauty/nautaux.h
nauty/nautest.c
nauty/nautest1.dre
nauty/nautest1a.ans
nauty/nautest1a.dre
nauty/nautest1b.ans
nauty/nautest1b.dre
nauty/nautest1c.ans
nauty/nautest1c.dre
nauty/nautest2.dre
nauty/nautest2a.ans
nauty/nautest2b.ans
nauty/nautest2c.ans
nauty/nautesta.ans
nauty/nautestb.ans
nauty/nautestc.ans
nauty/nautestd.ans
nauty/nauteste.ans
nauty/nautestf.ans
nauty/nautestg.ans
nauty/nauthread1.c
nauty/nauthread2.c
nauty/nautil.c
nauty/nautinv.c
nauty/nautinv.h
pynauty_nice.egg-info/PKG-INFO
pynauty_nice.egg-info/SOURCES.txt
pynauty_nice.egg-info/dependency_links.txt
pynauty_nice.egg-info/top_level.txt
