Metadata-Version: 1.1
Name: pynauty-nice
Version: 0.1.7
Summary: Automorphism and isomorphism of graphs
Home-page: https://github.com/michaelRadigan/pynauty-nice
Author: Michael Radigan
Author-email: michael@radigan.co.uk
License: GNU General Public License v3
Platform: Linux
Platform: Unix
Platform: OS X
Classifier: Environment :: Console
Classifier: Operating System :: POSIX :: Linux
Classifier: Operating System :: Unix
Classifier: Programming Language :: Python
Classifier: Programming Language :: Python :: 2.7
Classifier: Programming Language :: Python :: 3.5
Classifier: Programming Language :: C
Classifier: Topic :: Scientific/Engineering
Classifier: Topic :: Scientific/Engineering :: Mathematics
Classifier: Intended Audience :: Science/Research
Classifier: Intended Audience :: Education
Classifier: License :: OSI Approved :: GNU General Public License v3 or later (GPLv3+)
